cloudinary_storage/__init__.py
cloudinary_storage/app_settings.py
cloudinary_storage/apps.py
cloudinary_storage/helpers.py
cloudinary_storage/storage.py
cloudinary_storage/validators.py
cloudinary_storage/management/__init__.py
cloudinary_storage/management/commands/__init__.py
cloudinary_storage/management/commands/collectstatic.py
cloudinary_storage/management/commands/deleteorphanedmedia.py
cloudinary_storage/management/commands/deleteredundantstatic.py
cloudinary_storage/templatetags/__init__.py
cloudinary_storage/templatetags/cloudinary_static.py
dj3_cloudinary_storage-0.0.6.dist-info/LICENSE
dj3_cloudinary_storage-0.0.6.dist-info/METADATA
dj3_cloudinary_storage-0.0.6.dist-info/WHEEL
dj3_cloudinary_storage-0.0.6.dist-info/top_level.txt
dj3_cloudinary_storage-0.0.6.dist-info/RECORD
