Metadata-Version: 2.1
Name: dj3-cloudinary-storage
Version: 0.0.6
Summary: Django package that provides Cloudinary storages for both media and static files as well as management commands for removing unnecessary files. 
Home-page: https://github.com/tiagocordeiro/dj3-cloudinary-storage
Author: Tiago Cordeiro
Author-email: tiago@mulhergorila.com
License: MIT
Keywords: django cloudinary storage
Platform: UNKNOWN
Classifier: Framework :: Django
Classifier: Environment :: Web Environment
Classifier: Development Status :: 4 - Beta
Classifier: Intended Audience :: Developers
Classifier: Operating System :: OS Independent
Classifier: Programming Language :: Python
Classifier: Programming Language :: Python :: 3
Classifier: Programming Language :: Python :: 3.5
Classifier: Programming Language :: Python :: 3.6
Classifier: Programming Language :: Python :: 3.7
Classifier: Programming Language :: Python :: 3.8
Classifier: Programming Language :: Python :: 3.9
Classifier: Topic :: Internet :: WWW/HTTP
Provides-Extra: video
License-File: LICENSE
